Metadata-Version: 2.1
Name: kubeark
Version: 0.0.1
Summary: kubeark for Alibaba Cloud PaaS Platform v0.0.1
Author: walker.wt
Author-email: walker.wt@alibaba-inc.com
